roi_space_datetime/__init__.py
roi_space_datetime/time_tools.py
roi_space_datetime/time_tools02.py
roi_space_datetime_t-0.0.9.dist-info/LICENSE
roi_space_datetime_t-0.0.9.dist-info/METADATA
roi_space_datetime_t-0.0.9.dist-info/WHEEL
roi_space_datetime_t-0.0.9.dist-info/top_level.txt
roi_space_datetime_t-0.0.9.dist-info/RECORD
